README
setup.py
copyblock/__init__.py
copyblock/urls.py
copyblock/utils.py
copyblock/views.py
copyblock/templatetags/__init__.py
copyblock/templatetags/copyblock_tags.py
django_copyblock.egg-info/PKG-INFO
django_copyblock.egg-info/SOURCES.txt
django_copyblock.egg-info/dependency_links.txt
django_copyblock.egg-info/top_level.txt