Metadata-Version: 1.1
Name: django-copyblock
Version: 0.5.3
Summary: Manage website copy as a directory of markdown-formatted files. Insert files as copy into your Django templates.
Home-page: http://github.com/sivy/django-copyblock/
Author: Steve Ivy
Author-email: steve@wallrazer.com
License: MIT License
Keywords: django copy markdown
Platform: UNKNOWN
Classifier: License :: OSI Approved :: MIT License
Classifier: Programming Language :: Python
Classifier: Framework :: Django
Classifier: Environment :: Web Environment
Classifier: Intended Audience :: Developers
Classifier: Operating System :: OS Independent
Classifier: Topic :: Internet :: WWW/HTTP
Classifier: Topic :: Utilities
Requires: markdown
